{
	"info": {
		"_postman_id": "70ba9217-8eee-415a-9753-8c25aa45370a",
		"name": "green_garden",
		"schema": "https://schema.getpostman.com/json/collection/v2.1.0/collection.json",
		"_exporter_id": "31698328"
	},
	"item": [
		{
			"name": "http://127.0.0.1:8000/api/product",
			"request": {
				"method": "POST",
				"header": [
					{
						"key": "Accept",
						"value": "application/json",
						"type": "text"
					},
					{
						"warning": "This is a duplicate header and will be overridden by the Content-Type header generated by Postman.",
						"key": "Content-Type",
						"value": "application/json",
						"type": "text"
					},
					{
						"key": "Authorization",
						"value": "Bearer 1|E7SSjqzOLfKKyAdFJcZGErOEjI2lG5kvLV5FE5Cz",
						"type": "text"
					}
				],
				"body": {
					"mode": "formdata",
					"formdata": [
						{
							"key": "name_product",
							"value": "Sandat",
							"type": "text"
						},
						{
							"key": "desc_product",
							"value": "Bunga kuning",
							"type": "text"
						},
						{
							"key": "price",
							"value": "5550000",
							"type": "text"
						},
						{
							"key": "stock",
							"value": "4",
							"type": "text"
						},
						{
							"key": "id_seller",
							"value": "1",
							"type": "text"
						},
						{
							"key": "id_category",
							"value": "1",
							"type": "text"
						},
						{
							"key": "img_product",
							"type": "file",
							"src": "/C:/Users/acer/Downloads/paku-sarang-burung-8D349.jpg"
						}
					]
				},
				"url": {
					"raw": "http://127.0.0.1:8000/api/product",
					"protocol": "http",
					"host": [
						"127",
						"0",
						"0",
						"1"
					],
					"port": "8000",
					"path": [
						"api",
						"product"
					]
				}
			},
			"response": []
		},
		{
			"name": "http://127.0.0.1:8000/api/login",
			"protocolProfileBehavior": {
				"disableBodyPruning": true
			},
			"request": {
				"method": "GET",
				"header": [
					{
						"key": "Accept",
						"value": "application/json",
						"type": "text"
					},
					{
						"key": "Content-Type",
						"value": "application/json",
						"type": "text"
					}
				],
				"body": {
					"mode": "formdata",
					"formdata": [
						{
							"key": "email",
							"value": "andi@student.undiksha.ac.id",
							"type": "text"
						},
						{
							"key": "password",
							"value": "12345678",
							"type": "text"
						},
						{
							"key": "device_name",
							"value": "mobile",
							"type": "text"
						}
					]
				},
				"url": {
					"raw": "http://127.0.0.1:8000/api/login",
					"protocol": "http",
					"host": [
						"127",
						"0",
						"0",
						"1"
					],
					"port": "8000",
					"path": [
						"api",
						"login"
					]
				}
			},
			"response": []
		}
	]
}